pyutiltool/__init__.py
pyutiltool/my_module.py
pyutiltool-3.5.dist-info/METADATA
pyutiltool-3.5.dist-info/WHEEL
pyutiltool-3.5.dist-info/top_level.txt
pyutiltool-3.5.dist-info/RECORD
