Metadata-Version: 2.1
Name: pyutiltool
Version: 3.5
Summary: Simple Python Utils Package
Author: Alan Paul
Author-email: testy9128@protonmail.com
Classifier: Programming Language :: Python :: 3
Classifier: License :: OSI Approved :: MIT License
Classifier: Operating System :: OS Independent
Requires-Python: >=3.6
Requires-Dist: requests
